debugbreak/__init__.py
debugbreak/debugbreak.dll
debugbreak/src/main.c
debugbreak-0.0.2.dist-info/LICENSE
debugbreak-0.0.2.dist-info/METADATA
debugbreak-0.0.2.dist-info/WHEEL
debugbreak-0.0.2.dist-info/top_level.txt
debugbreak-0.0.2.dist-info/RECORD
