Metadata-Version: 2.1
Name: debugbreak
Version: 0.0.2
Summary: Trigger Visual Studio debugging mode from the current Python session.
Author: Andrej730
Classifier: Programming Language :: Python :: 3
Classifier: License :: OSI Approved :: MIT License
Classifier: Operating System :: OS Independent
Requires-Python: >=3.8
License-File: LICENSE
